{
  "en": {
    "tabs": {
      "config": "Config",
      "rules": "Rules",
      "logs": "Logs"
    },
    "config": {
      "title": "Configuration",
      "reload": "Reload",
      "save": "Save",
      "loadSuccess": "Configuration loaded.",
      "loadDefault": "No config file found, using defaults.",
      "loadError": "Failed to read config, using default values.",
      "saveSuccess": "Configuration saved.",
      "saveFailed": "Failed to save configuration.",
      "saveError": "An error occurred while saving.",
      "pathLabel": "Config file path",

      "moduleDir": "Module Directory",
      "tempDir": "Temporary Directory",
      "mountSource": "Mount Source",
      "logFile": "Log File",
      "partitions": "Partitions",
      "verboseLabel": "Log Level",
      "verboseOff": "Info",
      "verboseOn": "Debug"
    },
    "rules": {
      "title": "Hybrid Mount Rules",
      "desc": "Define mount strategies for specific paths. Default is recursive Bind Mount.",
      "reload": "Reload",
      "save": "Save Rules",
      "add": "Add Rule",
      "importBtn": "Import from Module",
      "importTitle": "Select Module to Import",
      "importDesc": "This will scan the module's system directory and add OverlayFS rules for detected paths.",
      "scanning": "Scanning...",
      "noModules": "No other modules found.",
      "cancel": "Cancel",
      "importResult": "Imported {0} rules from {1}",
      "pathHeader": "Path",
      "modeHeader": "Mode",
      "actionHeader": "Action",
      "modeOverlay": "OverlayFS",
      "modeBind": "Bind Mount",
      "saveSuccess": "Rules saved successfully.",
      "saveFailed": "Failed to save rules."
    },
    "logs": {
      "title": "Log Viewer",
      "select": "Log File",
      "refresh": "Refresh",
      "empty": "(empty)",
      "readFailed": "Failed to read log file.",
      "readException": "An exception occurred while reading log.",
      "current": "Current Log",
      "old": "Old Log"
    }
  },

  "zh": {
    "tabs": {
      "config": "配置",
      "rules": "规则",
      "logs": "日志"
    },
    "config": {
      "title": "配置",
      "reload": "重载",
      "save": "保存",
      "loadSuccess": "已从配置文件加载。",
      "loadDefault": "未找到配置文件，已使用默认配置。",
      "loadError": "读取配置失败，已使用默认配置。",
      "saveSuccess": "配置已保存。",
      "saveFailed": "保存失败，请检查权限或日志。",
      "saveError": "保存配置时发生错误。",
      "pathLabel": "配置文件路径",

      "moduleDir": "模块目录",
      "tempDir": "临时目录",
      "mountSource": "挂载源",
      "logFile": "日志文件",
      "partitions": "分区列表",
      "verboseLabel": "日志级别",
      "verboseOff": "信息",
      "verboseOn": "调试"
    },
    "rules": {
      "title": "混合挂载规则",
      "desc": "为特定路径定义挂载策略。默认为递归绑定挂载 (Bind Mount)。",
      "reload": "重载",
      "save": "保存规则",
      "add": "添加规则",
      "importBtn": "从模块导入",
      "importTitle": "选择要导入的模块",
      "importDesc": "这将扫描模块的 system 目录，并为检测到的路径添加 OverlayFS 规则。",
      "scanning": "扫描中...",
      "noModules": "未发现其他模块。",
      "cancel": "取消",
      "importResult": "已从 {1} 导入 {0} 条规则",
      "pathHeader": "路径",
      "modeHeader": "模式",
      "actionHeader": "操作",
      "modeOverlay": "OverlayFS (无痕)",
      "modeBind": "Bind Mount (兼容)",
      "saveSuccess": "规则保存成功。",
      "saveFailed": "保存规则失败。"
    },
    "logs": {
      "title": "日志查看",
      "select": "日志文件",
      "refresh": "刷新",
      "empty": "（空日志）",
      "readFailed": "读取日志失败。",
      "readException": "读取日志时发生异常。",
      "current": "当前日志",
      "old": "旧日志"
    }
  }
}